func/__init__.py
func/add.py
func/sub.py
simpleaddfunc/__init__.py
simpleaddfunc/add.py
simpleaddfunc/sub.py
simpleaddfunc1/__init__.py
simpleaddfunc1/add.py
simpleaddfunc1/sub.py
simpleaddfunc1-0.0.2.dist-info/METADATA
simpleaddfunc1-0.0.2.dist-info/WHEEL
simpleaddfunc1-0.0.2.dist-info/top_level.txt
simpleaddfunc1-0.0.2.dist-info/RECORD
