Metadata-Version: 2.1
Name: simpleaddfunc1
Version: 0.0.2
Summary: My first Python package
Home-page: UNKNOWN
Author: NS
License: UNKNOWN
Platform: UNKNOWN
Requires-Python: >=3.6
